practice_hello/__init__.py
practice_hello/main.py
practice_hello-0.4.dist-info/METADATA
practice_hello-0.4.dist-info/WHEEL
practice_hello-0.4.dist-info/top_level.txt
practice_hello-0.4.dist-info/RECORD
