Metadata-Version: 2.1
Name: practice-hello
Version: 0.4
